rusterize/__init__.py
rusterize/py.typed
rusterize/rusterize.pyi
rusterize/rusterize.pypy311-pp73-x86_64-linux-gnu.so
rusterize-0.6.1.dist-info/METADATA
rusterize-0.6.1.dist-info/WHEEL
rusterize-0.6.1.dist-info/licenses/LICENSE
rusterize-0.6.1.dist-info/RECORD
