Metadata-Version: 2.4
Name: rusterize
Version: 0.6.1
Classifier: License :: OSI Approved :: MIT License
Classifier: Operating System :: OS Independent
Classifier: Programming Language :: Rust
Classifier: Programming Language :: Python :: Implementation :: CPython
Classifier: Programming Language :: Python :: Implementation :: PyPy
Requires-Dist: geopandas>=1.0.1
Requires-Dist: pandas>=2.2.3
Requires-Dist: pyarrow>=18.1.0
Requires-Dist: polars>=1.19.0
Requires-Dist: xarray>=2025.1.1 ; extra == 'xarray'
Requires-Dist: rioxarray>=0.18.2 ; extra == 'xarray'
Provides-Extra: xarray
License-File: LICENSE
Summary: High performance rasterization tool for Python built in Rust
Keywords: rust,fast,raster,geometry,geopandas,xarray
Requires-Python: >=3.11
Project-URL: repository, https://github.com/ttrotto/rusterize
